<?xml version="1.0"?>
<PropertyList>

<model>
  <path>Models/Effects/pos_lamp_red_light_2st.xml</path>
  <offsets>
    <x-m>406.976</x-m>
    <y-m>-276.101</y-m>
    <z-m>60.972</z-m>
    <pitch-deg> 0.00</pitch-deg>
    <heading-deg>0.0 </heading-deg>
  </offsets>
</model>

<model>
  <path>Models/Effects/pos_lamp_red_light_2st.xml</path>
  <offsets>
    <x-m>356.283</x-m>
    <y-m>-222.909</y-m>
    <z-m>60.972</z-m>
    <pitch-deg> 0.00</pitch-deg>
    <heading-deg>0.0 </heading-deg>
  </offsets>
</model>

<model>
  <path>Models/Effects/pos_lamp_red_light_2st.xml</path>
  <offsets>
    <x-m>280.22</x-m>
    <y-m>-228.89</y-m>
    <z-m>60.972</z-m>
    <pitch-deg> 0.00</pitch-deg>
    <heading-deg>0.0 </heading-deg>
  </offsets>
</model>

<model>
  <path>Models/Effects/pos_lamp_red_light_2st.xml</path>
  <offsets>
    <x-m>342.807</x-m>
    <y-m>-242.234</y-m>
    <z-m>60.972</z-m>
    <pitch-deg> 0.00</pitch-deg>
    <heading-deg>0.0 </heading-deg>
  </offsets>
</model>

<model>
  <path>Models/Effects/pos_lamp_red_light_2st.xml</path>
  <offsets>
    <x-m>279.39</x-m>
    <y-m>426.918</y-m>
    <z-m>43.4016</z-m>
    <pitch-deg> 0.00</pitch-deg>
    <heading-deg>0.0 </heading-deg>
  </offsets>
</model>

<model>
  <path>Models/Effects/pos_lamp_red_light_2st.xml</path>
  <offsets>
    <x-m>295.424</x-m>
    <y-m>423.886</y-m>
    <z-m>43.4016</z-m>
    <pitch-deg> 0.00</pitch-deg>
    <heading-deg>0.0 </heading-deg>
  </offsets>
</model>

<model>
  <path>Models/Effects/pos_lamp_red_light_2st.xml</path>
  <offsets>
    <x-m>302.67</x-m>
    <y-m>418.733</y-m>
    <z-m>43.4016</z-m>
    <pitch-deg> 0.00</pitch-deg>
    <heading-deg>0.0 </heading-deg>
  </offsets>
</model>

<model>
  <path>Models/Effects/pos_lamp_red_light_2st.xml</path>
  <offsets>
    <x-m>300.961</x-m>
    <y-m>445.976</y-m>
    <z-m>43.4016</z-m>
    <pitch-deg> 0.00</pitch-deg>
    <heading-deg>0.0 </heading-deg>
  </offsets>
</model>

<model>
  <path>Models/Effects/pos_lamp_red_light_2st.xml</path>
  <offsets>
    <x-m>391.54</x-m>
    <y-m>357.257</y-m>
    <z-m>36.484</z-m>
    <pitch-deg> 0.00</pitch-deg>
    <heading-deg>0.0 </heading-deg>
  </offsets>
</model>

<model>
  <path>Models/Effects/pos_lamp_red_light_2st.xml</path>
  <offsets>
    <x-m>366.161</x-m>
    <y-m>368.157</y-m>
    <z-m>36.484</z-m>
    <pitch-deg> 0.00</pitch-deg>
    <heading-deg>0.0 </heading-deg>
  </offsets>
</model>

<model>
  <path>Models/Effects/pos_lamp_red_light_2st.xml</path>
  <offsets>
    <x-m>368.221</x-m>
    <y-m>380.967</y-m>
    <z-m>36.484</z-m>
    <pitch-deg> 0.00</pitch-deg>
    <heading-deg>0.0 </heading-deg>
  </offsets>
</model>

<model>
  <path>Models/Effects/pos_lamp_red_light_2st.xml</path>
  <offsets>
    <x-m>347.701</x-m>
    <y-m>394.392</y-m>
    <z-m>36.484</z-m>
    <pitch-deg> 0.00</pitch-deg>
    <heading-deg>0.0 </heading-deg>
  </offsets>
</model>

<model>
  <path>Models/Effects/pos_lamp_red_light_2st.xml</path>
  <offsets>
    <x-m>204.291</x-m>
    <y-m>404.798</y-m>
    <z-m>43.0039</z-m>
    <pitch-deg> 0.00</pitch-deg>
    <heading-deg>0.0 </heading-deg>
  </offsets>
</model>

<model>
  <path>Models/Effects/pos_lamp_red_light_2st.xml</path>
  <offsets>
    <x-m>228.856</x-m>
    <y-m>392.706</y-m>
    <z-m>43.0039</z-m>
    <pitch-deg> 0.00</pitch-deg>
    <heading-deg>0.0 </heading-deg>
  </offsets>
</model>

<model>
  <path>Models/Effects/pos_lamp_red_light_2st.xml</path>
  <offsets>
    <x-m>227.621</x-m>
    <y-m>383.569</y-m>
    <z-m>43.0039</z-m>
    <pitch-deg> 0.00</pitch-deg>
    <heading-deg>0.0 </heading-deg>
  </offsets>
</model>

<model>
  <path>Models/Effects/pos_lamp_red_light_2st.xml</path>
  <offsets>
    <x-m>246.358</x-m>
    <y-m>371.127</y-m>
    <z-m>43.0039</z-m>
    <pitch-deg> 0.00</pitch-deg>
    <heading-deg>0.0 </heading-deg>
  </offsets>
</model>

<model>
  <path>Models/Effects/pos_lamp_red_light_2st.xml</path>
  <offsets>
    <x-m>489.107</x-m>
    <y-m>8281.15</y-m>
    <z-m>49.4231</z-m>
    <pitch-deg> 0.00</pitch-deg>
    <heading-deg>0.0 </heading-deg>
  </offsets>
</model>

<model>
  <path>Models/Effects/pos_lamp_red_light_2st.xml</path>
  <offsets>
    <x-m>463.494</x-m>
    <y-m>8292.03</y-m>
    <z-m>49.4231</z-m>
    <pitch-deg> 0.00</pitch-deg>
    <heading-deg>0.0 </heading-deg>
  </offsets>
</model>

<model>
  <path>Models/Effects/pos_lamp_red_light_2st.xml</path>
  <offsets>
    <x-m>466.535</x-m>
    <y-m>8305.28</y-m>
    <z-m>49.4231</z-m>
    <pitch-deg> 0.00</pitch-deg>
    <heading-deg>0.0 </heading-deg>
  </offsets>
</model>

<model>
  <path>Models/Effects/pos_lamp_red_light_2st.xml</path>
  <offsets>
    <x-m>444.171</x-m>
    <y-m>8318.73</y-m>
    <z-m>49.4231</z-m>
    <pitch-deg> 0.00</pitch-deg>
    <heading-deg>0.0 </heading-deg>
  </offsets>
</model>

<model>
  <path>Models/Effects/pos_lamp_red_light_2st.xml</path>
  <offsets>
    <x-m>336.772</x-m>
    <y-m>488.794</y-m>
    <z-m>46.9814</z-m>
    <pitch-deg> 0.00</pitch-deg>
    <heading-deg>0.0 </heading-deg>
  </offsets>
</model>

<model>
  <path>Models/Effects/pos_lamp_red_light_2st.xml</path>
  <offsets>
    <x-m>313.317</x-m>
    <y-m>499.514</y-m>
    <z-m>46.9814</z-m>
    <pitch-deg> 0.00</pitch-deg>
    <heading-deg>0.0 </heading-deg>
  </offsets>
</model>

<model>
  <path>Models/Effects/pos_lamp_red_light_2st.xml</path>
  <offsets>
    <x-m>311.762</x-m>
    <y-m>514.567</y-m>
    <z-m>46.9814</z-m>
    <pitch-deg> 0.00</pitch-deg>
    <heading-deg>0.0 </heading-deg>
  </offsets>
</model>

<model>
  <path>Models/Effects/pos_lamp_red_light_2st.xml</path>
  <offsets>
    <x-m>295.313</x-m>
    <y-m>525.135</y-m>
    <z-m>46.9814</z-m>
    <pitch-deg> 0.00</pitch-deg>
    <heading-deg>0.0 </heading-deg>
  </offsets>
</model>

<model>
  <path>Models/Effects/pos_lamp_red_light_2st.xml</path>
  <offsets>
    <x-m>192.797</x-m>
    <y-m>423.556</y-m>
    <z-m>41.499</z-m>
    <pitch-deg> 0.00</pitch-deg>
    <heading-deg>0.0 </heading-deg>
  </offsets>
</model>

<model>
  <path>Models/Effects/pos_lamp_red_light_2st.xml</path>
  <offsets>
    <x-m>168.061</x-m>
    <y-m>434.348</y-m>
    <z-m>41.499</z-m>
    <pitch-deg> 0.00</pitch-deg>
    <heading-deg>0.0 </heading-deg>
  </offsets>
</model>

<model>
  <path>Models/Effects/pos_lamp_red_light_2st.xml</path>
  <offsets>
    <x-m>169.77</x-m>
    <y-m>448.709</y-m>
    <z-m>41.499</z-m>
    <pitch-deg> 0.00</pitch-deg>
    <heading-deg>0.0 </heading-deg>
  </offsets>
</model>

<model>
  <path>Models/Effects/pos_lamp_red_light_2st.xml</path>
  <offsets>
    <x-m>149.527</x-m>
    <y-m>458.033</y-m>
    <z-m>41.499</z-m>
    <pitch-deg> 0.00</pitch-deg>
    <heading-deg>0.0 </heading-deg>
  </offsets>
</model>

<model>
  <path>Models/Effects/pos_lamp_red_light_2st.xml</path>
  <offsets>
    <x-m>282.967</x-m>
    <y-m>557.857</y-m>
    <z-m>66.3043</z-m>
    <pitch-deg> 0.00</pitch-deg>
    <heading-deg>0.0 </heading-deg>
  </offsets>
</model>

<model>
  <path>Models/Effects/pos_lamp_red_light_2st.xml</path>
  <offsets>
    <x-m>333.173</x-m>
    <y-m>577.018</y-m>
    <z-m>66.3043</z-m>
    <pitch-deg> 0.00</pitch-deg>
    <heading-deg>0.0 </heading-deg>
  </offsets>
</model>

<model>
  <path>Models/Effects/pos_lamp_red_light_2st.xml</path>
  <offsets>
    <x-m>319.4</x-m>
    <y-m>613.514</y-m>
    <z-m>66.3043</z-m>
    <pitch-deg> 0.00</pitch-deg>
    <heading-deg>0.0 </heading-deg>
  </offsets>
</model>

<model>
  <path>Models/Effects/pos_lamp_red_light_2st.xml</path>
  <offsets>
    <x-m>269.123</x-m>
    <y-m>594.54</y-m>
    <z-m>66.3043</z-m>
    <pitch-deg> 0.00</pitch-deg>
    <heading-deg>0.0 </heading-deg>
  </offsets>
</model>

<model>
  <path>Models/Effects/pos_lamp_red_light_2st.xml</path>
  <offsets>
    <x-m>-421.603</x-m>
    <y-m>544.014</y-m>
    <z-m>48.3079</z-m>
    <pitch-deg> 0.00</pitch-deg>
    <heading-deg>0.0 </heading-deg>
  </offsets>
</model>

<model>
  <path>Models/Effects/pos_lamp_red_light_2st.xml</path>
  <offsets>
    <x-m>-402.951</x-m>
    <y-m>566.875</y-m>
    <z-m>48.3079</z-m>
    <pitch-deg> 0.00</pitch-deg>
    <heading-deg>0.0 </heading-deg>
  </offsets>
</model>

<model>
  <path>Models/Effects/pos_lamp_red_light_2st.xml</path>
  <offsets>
    <x-m>-421.567</x-m>
    <y-m>592.524</y-m>
    <z-m>48.3079</z-m>
    <pitch-deg> 0.00</pitch-deg>
    <heading-deg>0.0 </heading-deg>
  </offsets>
</model>

<model>
  <path>Models/Effects/pos_lamp_red_light_2st.xml</path>
  <offsets>
    <x-m>-440.941</x-m>
    <y-m>568.65</y-m>
    <z-m>48.3079</z-m>
    <pitch-deg> 0.00</pitch-deg>
    <heading-deg>0.0 </heading-deg>
  </offsets>
</model>

<model>
  <path>Models/Effects/pos_lamp_red_light_2st.xml</path>
  <offsets>
    <x-m>-68.9576</x-m>
    <y-m>184.183</y-m>
    <z-m>63.546</z-m>
    <pitch-deg> 0.00</pitch-deg>
    <heading-deg>0.0 </heading-deg>
  </offsets>
</model>

<model>
  <path>Models/Effects/pos_lamp_red_light_2st.xml</path>
  <offsets>
    <x-m>-57.0233</x-m>
    <y-m>167.354</y-m>
    <z-m>63.546</z-m>
    <pitch-deg> 0.00</pitch-deg>
    <heading-deg>0.0 </heading-deg>
  </offsets>
</model>

<model>
  <path>Models/Effects/pos_lamp_red_light_2st.xml</path>
  <offsets>
    <x-m>-39.7734</x-m>
    <y-m>182.573</y-m>
    <z-m>63.546</z-m>
    <pitch-deg> 0.00</pitch-deg>
    <heading-deg>0.0 </heading-deg>
  </offsets>
</model>

<model>
  <path>Models/Effects/pos_lamp_red_light_2st.xml</path>
  <offsets>
    <x-m>-58.4363</x-m>
    <y-m>195.329</y-m>
    <z-m>63.546</z-m>
    <pitch-deg> 0.00</pitch-deg>
    <heading-deg>0.0 </heading-deg>
  </offsets>
</model>

<model>
  <path>Models/Effects/pos_lamp_red_light_2st.xml</path>
  <offsets>
    <x-m>-30.7443</x-m>
    <y-m>199.285</y-m>
    <z-m>63.3628</z-m>
    <pitch-deg> 0.00</pitch-deg>
    <heading-deg>0.0 </heading-deg>
  </offsets>
</model>

<model>
  <path>Models/Effects/pos_lamp_red_light_2st.xml</path>
  <offsets>
    <x-m>-35.5598</x-m>
    <y-m>187.749</y-m>
    <z-m>63.3628</z-m>
    <pitch-deg> 0.00</pitch-deg>
    <heading-deg>0.0 </heading-deg>
  </offsets>
</model>

<model>
  <path>Models/Effects/pos_lamp_red_light_2st.xml</path>
  <offsets>
    <x-m>-22.3486</x-m>
    <y-m>182.658</y-m>
    <z-m>63.3628</z-m>
    <pitch-deg> 0.00</pitch-deg>
    <heading-deg>0.0 </heading-deg>
  </offsets>
</model>

<model>
  <path>Models/Effects/pos_lamp_red_light_2st.xml</path>
  <offsets>
    <x-m>-11.6955</x-m>
    <y-m>196.16</y-m>
    <z-m>63.3628</z-m>
    <pitch-deg> 0.00</pitch-deg>
    <heading-deg>0.0 </heading-deg>
  </offsets>
</model>

<model>
  <path>Models/Effects/pos_lamp_red_light_2st.xml</path>
  <offsets>
    <x-m>-152.474</x-m>
    <y-m>444.958</y-m>
    <z-m>43.0277</z-m>
    <pitch-deg> 0.00</pitch-deg>
    <heading-deg>0.0 </heading-deg>
  </offsets>
</model>

<model>
  <path>Models/Effects/pos_lamp_red_light_2st.xml</path>
  <offsets>
    <x-m>-138.518</x-m>
    <y-m>434.894</y-m>
    <z-m>43.0277</z-m>
    <pitch-deg> 0.00</pitch-deg>
    <heading-deg>0.0 </heading-deg>
  </offsets>
</model>

<model>
  <path>Models/Effects/pos_lamp_red_light_2st.xml</path>
  <offsets>
    <x-m>-128.32</x-m>
    <y-m>448.587</y-m>
    <z-m>43.0277</z-m>
    <pitch-deg> 0.00</pitch-deg>
    <heading-deg>0.0 </heading-deg>
  </offsets>
</model>

<model>
  <path>Models/Effects/pos_lamp_red_light_2st.xml</path>
  <offsets>
    <x-m>-143.004</x-m>
    <y-m>458.538</y-m>
    <z-m>43.0277</z-m>
    <pitch-deg> 0.00</pitch-deg>
    <heading-deg>0.0 </heading-deg>
  </offsets>
</model>

<model>
  <path>Models/Effects/pos_lamp_red_light_2st.xml</path>
  <offsets>
    <x-m>-164.626</x-m>
    <y-m>-142.264</y-m>
    <z-m>52.8663</z-m>
    <pitch-deg> 0.00</pitch-deg>
    <heading-deg>0.0 </heading-deg>
  </offsets>
</model>

<model>
  <path>Models/Effects/pos_lamp_red_light_2st.xml</path>
  <offsets>
    <x-m>-118.982</x-m>
    <y-m>-110.45</y-m>
    <z-m>52.8663</z-m>
    <pitch-deg> 0.00</pitch-deg>
    <heading-deg>0.0 </heading-deg>
  </offsets>
</model>

<model>
  <path>Models/Effects/pos_lamp_red_light_2st.xml</path>
  <offsets>
    <x-m>-135.725</x-m>
    <y-m>-80.2133</y-m>
    <z-m>52.8663</z-m>
    <pitch-deg> 0.00</pitch-deg>
    <heading-deg>0.0 </heading-deg>
  </offsets>
</model>

<model>
  <path>Models/Effects/pos_lamp_red_light_2st.xml</path>
  <offsets>
    <x-m>-140.298</x-m>
    <y-m>-83.3793</y-m>
    <z-m>52.8663</z-m>
    <pitch-deg> 0.00</pitch-deg>
    <heading-deg>0.0 </heading-deg>
  </offsets>
</model>

<model>
  <path>Models/Effects/pos_lamp_red_light_2st.xml</path>
  <offsets>
    <x-m>144.955</x-m>
    <y-m>-152.383</y-m>
    <z-m>89.6515</z-m>
    <pitch-deg> 0.00</pitch-deg>
    <heading-deg>0.0 </heading-deg>
  </offsets>
</model>

<model>
  <path>Models/Effects/pos_lamp_red_light_2st.xml</path>
  <offsets>
    <x-m>127.216</x-m>
    <y-m>-110.589</y-m>
    <z-m>89.6515</z-m>
    <pitch-deg> 0.00</pitch-deg>
    <heading-deg>0.0 </heading-deg>
  </offsets>
</model>

<model>
  <path>Models/Effects/pos_lamp_red_light_2st.xml</path>
  <offsets>
    <x-m>95.2084</x-m>
    <y-m>-124.173</y-m>
    <z-m>89.6515</z-m>
    <pitch-deg> 0.00</pitch-deg>
    <heading-deg>0.0 </heading-deg>
  </offsets>
</model>

<model>
  <path>Models/Effects/pos_lamp_red_light_2st.xml</path>
  <offsets>
    <x-m>112.947</x-m>
    <y-m>-165.968</y-m>
    <z-m>89.6515</z-m>
    <pitch-deg> 0.00</pitch-deg>
    <heading-deg>0.0 </heading-deg>
  </offsets>
</model>

<model>
  <path>Models/Effects/pos_lamp_red_light_2st.xml</path>
  <offsets>
    <x-m>-349.733</x-m>
    <y-m>616.993</y-m>
    <z-m>52.8446</z-m>
    <pitch-deg> 0.00</pitch-deg>
    <heading-deg>0.0 </heading-deg>
  </offsets>
</model>

<model>
  <path>Models/Effects/pos_lamp_red_light_2st.xml</path>
  <offsets>
    <x-m>-401.334</x-m>
    <y-m>585.079</y-m>
    <z-m>52.8446</z-m>
    <pitch-deg> 0.00</pitch-deg>
    <heading-deg>0.0 </heading-deg>
  </offsets>
</model>

<model>
  <path>Models/Effects/pos_lamp_red_light_2st.xml</path>
  <offsets>
    <x-m>-384.849</x-m>
    <y-m>573.52</y-m>
    <z-m>52.8446</z-m>
    <pitch-deg> 0.00</pitch-deg>
    <heading-deg>0.0 </heading-deg>
  </offsets>
</model>

<model>
  <path>Models/Effects/pos_lamp_red_light_2st.xml</path>
  <offsets>
    <x-m>-360.023</x-m>
    <y-m>602.319</y-m>
    <z-m>52.8446</z-m>
    <pitch-deg> 0.00</pitch-deg>
    <heading-deg>0.0 </heading-deg>
  </offsets>
</model>

<model>
  <path>Models/Effects/pos_lamp_red_light_2st.xml</path>
  <offsets>
    <x-m>118.827</x-m>
    <y-m>398.167</y-m>
    <z-m>51.4595</z-m>
    <pitch-deg> 0.00</pitch-deg>
    <heading-deg>0.0 </heading-deg>
  </offsets>
</model>

<model>
  <path>Models/Effects/pos_lamp_red_light_2st.xml</path>
  <offsets>
    <x-m>95.4596</x-m>
    <y-m>417.149</y-m>
    <z-m>51.4595</z-m>
    <pitch-deg> 0.00</pitch-deg>
    <heading-deg>0.0 </heading-deg>
  </offsets>
</model>

<model>
  <path>Models/Effects/pos_lamp_red_light_2st.xml</path>
  <offsets>
    <x-m>98.5969</x-m>
    <y-m>429.48</y-m>
    <z-m>51.4595</z-m>
    <pitch-deg> 0.00</pitch-deg>
    <heading-deg>0.0 </heading-deg>
  </offsets>
</model>

<model>
  <path>Models/Effects/pos_lamp_red_light_2st.xml</path>
  <offsets>
    <x-m>79.185</x-m>
    <y-m>436.664</y-m>
    <z-m>51.4595</z-m>
    <pitch-deg> 0.00</pitch-deg>
    <heading-deg>0.0 </heading-deg>
  </offsets>
</model>

<model>
  <path>Models/Effects/pos_lamp_red_light_2st.xml</path>
  <offsets>
    <x-m>81.3</x-m>
    <y-m>506.727</y-m>
    <z-m>38.8054</z-m>
    <pitch-deg> 0.00</pitch-deg>
    <heading-deg>0.0 </heading-deg>
  </offsets>
</model>

<model>
  <path>Models/Effects/pos_lamp_red_light_2st.xml</path>
  <offsets>
    <x-m>70.5479</x-m>
    <y-m>460.063</y-m>
    <z-m>38.8054</z-m>
    <pitch-deg> 0.00</pitch-deg>
    <heading-deg>0.0 </heading-deg>
  </offsets>
</model>

<model>
  <path>Models/Effects/pos_lamp_red_light_2st.xml</path>
  <offsets>
    <x-m>73.5115</x-m>
    <y-m>477.441</y-m>
    <z-m>38.8054</z-m>
    <pitch-deg> 0.00</pitch-deg>
    <heading-deg>0.0 </heading-deg>
  </offsets>
</model>

<model>
  <path>Models/Effects/pos_lamp_red_light_2st.xml</path>
  <offsets>
    <x-m>69.9746</x-m>
    <y-m>487.043</y-m>
    <z-m>38.8054</z-m>
    <pitch-deg> 0.00</pitch-deg>
    <heading-deg>0.0 </heading-deg>
  </offsets>
</model>

<model>
  <path>Models/Effects/pos_lamp_red_light_2st.xml</path>
  <offsets>
    <x-m>516.746</x-m>
    <y-m>8427.35</y-m>
    <z-m>38.7017</z-m>
    <pitch-deg> 0.00</pitch-deg>
    <heading-deg>0.0 </heading-deg>
  </offsets>
</model>

<model>
  <path>Models/Effects/pos_lamp_red_light_2st.xml</path>
  <offsets>
    <x-m>541.888</x-m>
    <y-m>8411.48</y-m>
    <z-m>38.7017</z-m>
    <pitch-deg> 0.00</pitch-deg>
    <heading-deg>0.0 </heading-deg>
  </offsets>
</model>

<model>
  <path>Models/Effects/pos_lamp_red_light_2st.xml</path>
  <offsets>
    <x-m>540.285</x-m>
    <y-m>8400.47</y-m>
    <z-m>38.7017</z-m>
    <pitch-deg> 0.00</pitch-deg>
    <heading-deg>0.0 </heading-deg>
  </offsets>
</model>

<model>
  <path>Models/Effects/pos_lamp_red_light_2st.xml</path>
  <offsets>
    <x-m>558.68</x-m>
    <y-m>8389.88</y-m>
    <z-m>38.7017</z-m>
    <pitch-deg> 0.00</pitch-deg>
    <heading-deg>0.0 </heading-deg>
  </offsets>
</model>

<model>
  <path>Models/Effects/pos_lamp_red_light_2st.xml</path>
  <offsets>
    <x-m>115.616</x-m>
    <y-m>406.902</y-m>
    <z-m>52.079</z-m>
    <pitch-deg> 0.00</pitch-deg>
    <heading-deg>0.0 </heading-deg>
  </offsets>
</model>

<model>
  <path>Models/Effects/pos_lamp_red_light_2st.xml</path>
  <offsets>
    <x-m>128.505</x-m>
    <y-m>454.154</y-m>
    <z-m>52.079</z-m>
    <pitch-deg> 0.00</pitch-deg>
    <heading-deg>0.0 </heading-deg>
  </offsets>
</model>

<model>
  <path>Models/Effects/pos_lamp_red_light_2st.xml</path>
  <offsets>
    <x-m>124.399</x-m>
    <y-m>437.509</y-m>
    <z-m>52.079</z-m>
    <pitch-deg> 0.00</pitch-deg>
    <heading-deg>0.0 </heading-deg>
  </offsets>
</model>

<model>
  <path>Models/Effects/pos_lamp_red_light_2st.xml</path>
  <offsets>
    <x-m>128.023</x-m>
    <y-m>428.328</y-m>
    <z-m>52.079</z-m>
    <pitch-deg> 0.00</pitch-deg>
    <heading-deg>0.0 </heading-deg>
  </offsets>
</model>

<model>
  <path>Models/Effects/pos_lamp_red_light_2st.xml</path>
  <offsets>
    <x-m>591.247</x-m>
    <y-m>8443.16</y-m>
    <z-m>28.2361</z-m>
    <pitch-deg> 0.00</pitch-deg>
    <heading-deg>0.0 </heading-deg>
  </offsets>
</model>

<model>
  <path>Models/Effects/pos_lamp_red_light_2st.xml</path>
  <offsets>
    <x-m>579.21</x-m>
    <y-m>8394.07</y-m>
    <z-m>28.2361</z-m>
    <pitch-deg> 0.00</pitch-deg>
    <heading-deg>0.0 </heading-deg>
  </offsets>
</model>

<model>
  <path>Models/Effects/pos_lamp_red_light_2st.xml</path>
  <offsets>
    <x-m>580.551</x-m>
    <y-m>8417.22</y-m>
    <z-m>28.2361</z-m>
    <pitch-deg> 0.00</pitch-deg>
    <heading-deg>0.0 </heading-deg>
  </offsets>
</model>

<model>
  <path>Models/Effects/pos_lamp_red_light_2st.xml</path>
  <offsets>
    <x-m>576.523</x-m>
    <y-m>8429.31</y-m>
    <z-m>28.2361</z-m>
    <pitch-deg> 0.00</pitch-deg>
    <heading-deg>0.0 </heading-deg>
  </offsets>
</model>

<model>
  <path>Models/Effects/pos_lamp_red_light_2st.xml</path>
  <offsets>
    <x-m>189.176</x-m>
    <y-m>432.827</y-m>
    <z-m>39.7045</z-m>
    <pitch-deg> 0.00</pitch-deg>
    <heading-deg>0.0 </heading-deg>
  </offsets>
</model>

<model>
  <path>Models/Effects/pos_lamp_red_light_2st.xml</path>
  <offsets>
    <x-m>200.834</x-m>
    <y-m>480.93</y-m>
    <z-m>39.7045</z-m>
    <pitch-deg> 0.00</pitch-deg>
    <heading-deg>0.0 </heading-deg>
  </offsets>
</model>

<model>
  <path>Models/Effects/pos_lamp_red_light_2st.xml</path>
  <offsets>
    <x-m>197.965</x-m>
    <y-m>461.363</y-m>
    <z-m>39.7045</z-m>
    <pitch-deg> 0.00</pitch-deg>
    <heading-deg>0.0 </heading-deg>
  </offsets>
</model>

<model>
  <path>Models/Effects/pos_lamp_red_light_2st.xml</path>
  <offsets>
    <x-m>202.113</x-m>
    <y-m>449.556</y-m>
    <z-m>39.7045</z-m>
    <pitch-deg> 0.00</pitch-deg>
    <heading-deg>0.0 </heading-deg>
  </offsets>
</model>

<model>
  <path>Models/Effects/pos_lamp_red_light_2st.xml</path>
  <offsets>
    <x-m>148.925</x-m>
    <y-m>539.79</y-m>
    <z-m>28.7854</z-m>
    <pitch-deg> 0.00</pitch-deg>
    <heading-deg>0.0 </heading-deg>
  </offsets>
</model>

<model>
  <path>Models/Effects/pos_lamp_red_light_2st.xml</path>
  <offsets>
    <x-m>171.869</x-m>
    <y-m>530.778</y-m>
    <z-m>28.7854</z-m>
    <pitch-deg> 0.00</pitch-deg>
    <heading-deg>0.0 </heading-deg>
  </offsets>
</model>

<model>
  <path>Models/Effects/pos_lamp_red_light_2st.xml</path>
  <offsets>
    <x-m>172.581</x-m>
    <y-m>517.802</y-m>
    <z-m>28.7854</z-m>
    <pitch-deg> 0.00</pitch-deg>
    <heading-deg>0.0 </heading-deg>
  </offsets>
</model>

<model>
  <path>Models/Effects/pos_lamp_red_light_2st.xml</path>
  <offsets>
    <x-m>192.203</x-m>
    <y-m>503.622</y-m>
    <z-m>28.7854</z-m>
    <pitch-deg> 0.00</pitch-deg>
    <heading-deg>0.0 </heading-deg>
  </offsets>
</model>

<model>
  <path>Models/Effects/pos_lamp_red_light_2st.xml</path>
  <offsets>
    <x-m>279.39</x-m>
    <y-m>426.918</y-m>
    <z-m>45.4526</z-m>
    <pitch-deg> 0.00</pitch-deg>
    <heading-deg>0.0 </heading-deg>
  </offsets>
</model>

<model>
  <path>Models/Effects/pos_lamp_red_light_2st.xml</path>
  <offsets>
    <x-m>269.756</x-m>
    <y-m>381.069</y-m>
    <z-m>45.4526</z-m>
    <pitch-deg> 0.00</pitch-deg>
    <heading-deg>0.0 </heading-deg>
  </offsets>
</model>

<model>
  <path>Models/Effects/pos_lamp_red_light_2st.xml</path>
  <offsets>
    <x-m>269.379</x-m>
    <y-m>404.359</y-m>
    <z-m>45.4526</z-m>
    <pitch-deg> 0.00</pitch-deg>
    <heading-deg>0.0 </heading-deg>
  </offsets>
</model>

<model>
  <path>Models/Effects/pos_lamp_red_light_2st.xml</path>
  <offsets>
    <x-m>266.343</x-m>
    <y-m>411.633</y-m>
    <z-m>45.4526</z-m>
    <pitch-deg> 0.00</pitch-deg>
    <heading-deg>0.0 </heading-deg>
  </offsets>
</model>

<model>
  <path>Models/Effects/pos_lamp_red_light_2st.xml</path>
  <offsets>
    <x-m>775.517</x-m>
    <y-m>8401.32</y-m>
    <z-m>49.4714</z-m>
    <pitch-deg> 0.00</pitch-deg>
    <heading-deg>0.0 </heading-deg>
  </offsets>
</model>

<model>
  <path>Models/Effects/pos_lamp_red_light_2st.xml</path>
  <offsets>
    <x-m>772.86</x-m>
    <y-m>8452.65</y-m>
    <z-m>49.4714</z-m>
    <pitch-deg> 0.00</pitch-deg>
    <heading-deg>0.0 </heading-deg>
  </offsets>
</model>

<model>
  <path>Models/Effects/pos_lamp_red_light_2st.xml</path>
  <offsets>
    <x-m>775.754</x-m>
    <y-m>8436.45</y-m>
    <z-m>49.4714</z-m>
    <pitch-deg> 0.00</pitch-deg>
    <heading-deg>0.0 </heading-deg>
  </offsets>
</model>

<model>
  <path>Models/Effects/pos_lamp_red_light_2st.xml</path>
  <offsets>
    <x-m>786.63</x-m>
    <y-m>8415.39</y-m>
    <z-m>49.4714</z-m>
    <pitch-deg> 0.00</pitch-deg>
    <heading-deg>0.0 </heading-deg>
  </offsets>
</model>

<model>
  <path>Models/Effects/pos_lamp_red_light_2st.xml</path>
  <offsets>
    <x-m>349.296</x-m>
    <y-m>460.61</y-m>
    <z-m>42.4228</z-m>
    <pitch-deg> 0.00</pitch-deg>
    <heading-deg>0.0 </heading-deg>
  </offsets>
</model>

<model>
  <path>Models/Effects/pos_lamp_red_light_2st.xml</path>
  <offsets>
    <x-m>338.765</x-m>
    <y-m>414.296</y-m>
    <z-m>42.4228</z-m>
    <pitch-deg> 0.00</pitch-deg>
    <heading-deg>0.0 </heading-deg>
  </offsets>
</model>

<model>
  <path>Models/Effects/pos_lamp_red_light_2st.xml</path>
  <offsets>
    <x-m>343.45</x-m>
    <y-m>436.864</y-m>
    <z-m>42.4228</z-m>
    <pitch-deg> 0.00</pitch-deg>
    <heading-deg>0.0 </heading-deg>
  </offsets>
</model>

<model>
  <path>Models/Effects/pos_lamp_red_light_2st.xml</path>
  <offsets>
    <x-m>338.045</x-m>
    <y-m>447.709</y-m>
    <z-m>42.4228</z-m>
    <pitch-deg> 0.00</pitch-deg>
    <heading-deg>0.0 </heading-deg>
  </offsets>
</model>

<model>
  <path>Models/Effects/pos_lamp_red_light_2st.xml</path>
  <offsets>
    <x-m>447.759</x-m>
    <y-m>8386.65</y-m>
    <z-m>42.2054</z-m>
    <pitch-deg> 0.00</pitch-deg>
    <heading-deg>0.0 </heading-deg>
  </offsets>
</model>

<model>
  <path>Models/Effects/pos_lamp_red_light_2st.xml</path>
  <offsets>
    <x-m>435.855</x-m>
    <y-m>8339.57</y-m>
    <z-m>42.2054</z-m>
    <pitch-deg> 0.00</pitch-deg>
    <heading-deg>0.0 </heading-deg>
  </offsets>
</model>

<model>
  <path>Models/Effects/pos_lamp_red_light_2st.xml</path>
  <offsets>
    <x-m>438.103</x-m>
    <y-m>8361.93</y-m>
    <z-m>42.2054</z-m>
    <pitch-deg> 0.00</pitch-deg>
    <heading-deg>0.0 </heading-deg>
  </offsets>
</model>

<model>
  <path>Models/Effects/pos_lamp_red_light_2st.xml</path>
  <offsets>
    <x-m>434.077</x-m>
    <y-m>8371.09</y-m>
    <z-m>42.2054</z-m>
    <pitch-deg> 0.00</pitch-deg>
    <heading-deg>0.0 </heading-deg>
  </offsets>
</model>

<model>
  <path>Models/Effects/pos_lamp_red_light_2st.xml</path>
  <offsets>
    <x-m>387.188</x-m>
    <y-m>369.56</y-m>
    <z-m>37.0615</z-m>
    <pitch-deg> 0.00</pitch-deg>
    <heading-deg>0.0 </heading-deg>
  </offsets>
</model>

<model>
  <path>Models/Effects/pos_lamp_red_light_2st.xml</path>
  <offsets>
    <x-m>399.059</x-m>
    <y-m>413.017</y-m>
    <z-m>37.0615</z-m>
    <pitch-deg> 0.00</pitch-deg>
    <heading-deg>0.0 </heading-deg>
  </offsets>
</model>

<model>
  <path>Models/Effects/pos_lamp_red_light_2st.xml</path>
  <offsets>
    <x-m>395.818</x-m>
    <y-m>391.174</y-m>
    <z-m>37.0615</z-m>
    <pitch-deg> 0.00</pitch-deg>
    <heading-deg>0.0 </heading-deg>
  </offsets>
</model>

<model>
  <path>Models/Effects/pos_lamp_red_light_2st.xml</path>
  <offsets>
    <x-m>400.485</x-m>
    <y-m>380.044</y-m>
    <z-m>37.0615</z-m>
    <pitch-deg> 0.00</pitch-deg>
    <heading-deg>0.0 </heading-deg>
  </offsets>
</model>

<model>
  <path>Models/Effects/pos_lamp_red_light_2st.xml</path>
  <offsets>
    <x-m>344.534</x-m>
    <y-m>469.716</y-m>
    <z-m>41.3684</z-m>
    <pitch-deg> 0.00</pitch-deg>
    <heading-deg>0.0 </heading-deg>
  </offsets>
</model>

<model>
  <path>Models/Effects/pos_lamp_red_light_2st.xml</path>
  <offsets>
    <x-m>370.631</x-m>
    <y-m>459.744</y-m>
    <z-m>41.3684</z-m>
    <pitch-deg> 0.00</pitch-deg>
    <heading-deg>0.0 </heading-deg>
  </offsets>
</model>

<model>
  <path>Models/Effects/pos_lamp_red_light_2st.xml</path>
  <offsets>
    <x-m>368.822</x-m>
    <y-m>446.717</y-m>
    <z-m>41.3684</z-m>
    <pitch-deg> 0.00</pitch-deg>
    <heading-deg>0.0 </heading-deg>
  </offsets>
</model>

<model>
  <path>Models/Effects/pos_lamp_red_light_2st.xml</path>
  <offsets>
    <x-m>390.433</x-m>
    <y-m>436.293</y-m>
    <z-m>41.3684</z-m>
    <pitch-deg> 0.00</pitch-deg>
    <heading-deg>0.0 </heading-deg>
  </offsets>
</model>

<model>
  <path>Models/Effects/pos_lamp_red_light_2st.xml</path>
  <offsets>
    <x-m>5.11586</x-m>
    <y-m>483.906</y-m>
    <z-m>40.5086</z-m>
    <pitch-deg> 0.00</pitch-deg>
    <heading-deg>0.0 </heading-deg>
  </offsets>
</model>

<model>
  <path>Models/Effects/pos_lamp_red_light_2st.xml</path>
  <offsets>
    <x-m>29.1117</x-m>
    <y-m>473.33</y-m>
    <z-m>40.5086</z-m>
    <pitch-deg> 0.00</pitch-deg>
    <heading-deg>0.0 </heading-deg>
  </offsets>
</model>

<model>
  <path>Models/Effects/pos_lamp_red_light_2st.xml</path>
  <offsets>
    <x-m>27.8509</x-m>
    <y-m>461.816</y-m>
    <z-m>40.5086</z-m>
    <pitch-deg> 0.00</pitch-deg>
    <heading-deg>0.0 </heading-deg>
  </offsets>
</model>

<model>
  <path>Models/Effects/pos_lamp_red_light_2st.xml</path>
  <offsets>
    <x-m>49.3315</x-m>
    <y-m>449.152</y-m>
    <z-m>40.5086</z-m>
    <pitch-deg> 0.00</pitch-deg>
    <heading-deg>0.0 </heading-deg>
  </offsets>
</model>

<model>
  <path>Models/Effects/pos_lamp_red_light_2st.xml</path>
  <offsets>
    <x-m>50.3613</x-m>
    <y-m>368.621</y-m>
    <z-m>50.4841</z-m>
    <pitch-deg> 0.00</pitch-deg>
    <heading-deg>0.0 </heading-deg>
  </offsets>
</model>

<model>
  <path>Models/Effects/pos_lamp_red_light_2st.xml</path>
  <offsets>
    <x-m>48.5319</x-m>
    <y-m>424.369</y-m>
    <z-m>50.4841</z-m>
    <pitch-deg> 0.00</pitch-deg>
    <heading-deg>0.0 </heading-deg>
  </offsets>
</model>

<model>
  <path>Models/Effects/pos_lamp_red_light_2st.xml</path>
  <offsets>
    <x-m>50.5778</x-m>
    <y-m>403.327</y-m>
    <z-m>50.4841</z-m>
    <pitch-deg> 0.00</pitch-deg>
    <heading-deg>0.0 </heading-deg>
  </offsets>
</model>

<model>
  <path>Models/Effects/pos_lamp_red_light_2st.xml</path>
  <offsets>
    <x-m>63.3077</x-m>
    <y-m>384.337</y-m>
    <z-m>50.4841</z-m>
    <pitch-deg> 0.00</pitch-deg>
    <heading-deg>0.0 </heading-deg>
  </offsets>
</model>

<model>
  <path>Models/Effects/pos_lamp_red_light_2st.xml</path>
  <offsets>
    <x-m>-265.65</x-m>
    <y-m>491.892</y-m>
    <z-m>29.2915</z-m>
    <pitch-deg> 0.00</pitch-deg>
    <heading-deg>0.0 </heading-deg>
  </offsets>
</model>

<model>
  <path>Models/Effects/pos_lamp_red_light_2st.xml</path>
  <offsets>
    <x-m>-260.307</x-m>
    <y-m>506.586</y-m>
    <z-m>29.2915</z-m>
    <pitch-deg> 0.00</pitch-deg>
    <heading-deg>0.0 </heading-deg>
  </offsets>
</model>

<model>
  <path>Models/Effects/pos_lamp_red_light_2st.xml</path>
  <offsets>
    <x-m>-249.011</x-m>
    <y-m>523.031</y-m>
    <z-m>29.2915</z-m>
    <pitch-deg> 0.00</pitch-deg>
    <heading-deg>0.0 </heading-deg>
  </offsets>
</model>

<model>
  <path>Models/Effects/pos_lamp_red_light_2st.xml</path>
  <offsets>
    <x-m>-238.086</x-m>
    <y-m>532.503</y-m>
    <z-m>29.2915</z-m>
    <pitch-deg> 0.00</pitch-deg>
    <heading-deg>0.0 </heading-deg>
  </offsets>
</model>

<model>
  <path>Models/Effects/pos_lamp_red_light_2st.xml</path>
  <offsets>
    <x-m>-62.5419</x-m>
    <y-m>425.083</y-m>
    <z-m>56.8415</z-m>
    <pitch-deg> 0.00</pitch-deg>
    <heading-deg>0.0 </heading-deg>
  </offsets>
</model>

<model>
  <path>Models/Effects/pos_lamp_red_light_2st.xml</path>
  <offsets>
    <x-m>-55.3664</x-m>
    <y-m>415.461</y-m>
    <z-m>56.8415</z-m>
    <pitch-deg> 0.00</pitch-deg>
    <heading-deg>0.0 </heading-deg>
  </offsets>
</model>

<model>
  <path>Models/Effects/pos_lamp_red_light_2st.xml</path>
  <offsets>
    <x-m>-27.9933</x-m>
    <y-m>353.06</y-m>
    <z-m>56.8415</z-m>
    <pitch-deg> 0.00</pitch-deg>
    <heading-deg>0.0 </heading-deg>
  </offsets>
</model>

<model>
  <path>Models/Effects/pos_lamp_red_light_2st.xml</path>
  <offsets>
    <x-m>-22.0912</x-m>
    <y-m>396.857</y-m>
    <z-m>56.8415</z-m>
    <pitch-deg> 0.00</pitch-deg>
    <heading-deg>0.0 </heading-deg>
  </offsets>
</model>

<model>
  <path>Models/Effects/pos_lamp_red_light_2st.xml</path>
  <offsets>
    <x-m>-137.929</x-m>
    <y-m>578.287</y-m>
    <z-m>48.7533</z-m>
    <pitch-deg> 0.00</pitch-deg>
    <heading-deg>0.0 </heading-deg>
  </offsets>
</model>

<model>
  <path>Models/Effects/pos_lamp_red_light_2st.xml</path>
  <offsets>
    <x-m>-110.434</x-m>
    <y-m>527.817</y-m>
    <z-m>48.7533</z-m>
    <pitch-deg> 0.00</pitch-deg>
    <heading-deg>0.0 </heading-deg>
  </offsets>
</model>

<model>
  <path>Models/Effects/pos_lamp_red_light_2st.xml</path>
  <offsets>
    <x-m>-74.9062</x-m>
    <y-m>509.134</y-m>
    <z-m>48.7533</z-m>
    <pitch-deg> 0.00</pitch-deg>
    <heading-deg>0.0 </heading-deg>
  </offsets>
</model>

<model>
  <path>Models/Effects/pos_lamp_red_light_2st.xml</path>
  <offsets>
    <x-m>-114.45</x-m>
    <y-m>574.023</y-m>
    <z-m>48.7533</z-m>
    <pitch-deg> 0.00</pitch-deg>
    <heading-deg>0.0 </heading-deg>
  </offsets>
</model>

<model>
  <path>Models/Effects/pos_lamp_red_light_2st.xml</path>
  <offsets>
    <x-m>932.282</x-m>
    <y-m>8147.42</y-m>
    <z-m>36.9276</z-m>
    <pitch-deg> 0.00</pitch-deg>
    <heading-deg>0.0 </heading-deg>
  </offsets>
</model>

<model>
  <path>Models/Effects/pos_lamp_red_light_2st.xml</path>
  <offsets>
    <x-m>936.898</x-m>
    <y-m>8177.76</y-m>
    <z-m>36.9276</z-m>
    <pitch-deg> 0.00</pitch-deg>
    <heading-deg>0.0 </heading-deg>
  </offsets>
</model>

<model>
  <path>Models/Effects/pos_lamp_red_light_2st.xml</path>
  <offsets>
    <x-m>964.152</x-m>
    <y-m>8188.5</y-m>
    <z-m>36.9276</z-m>
    <pitch-deg> 0.00</pitch-deg>
    <heading-deg>0.0 </heading-deg>
  </offsets>
</model>

<model>
  <path>Models/Effects/pos_lamp_red_light_2st.xml</path>
  <offsets>
    <x-m>973.002</x-m>
    <y-m>8164.44</y-m>
    <z-m>36.9276</z-m>
    <pitch-deg> 0.00</pitch-deg>
    <heading-deg>0.0 </heading-deg>
  </offsets>
</model>

<model>
  <path>Models/Effects/pos_lamp_red_light_2st.xml</path>
  <offsets>
    <x-m>521.098</x-m>
    <y-m>168.145</y-m>
    <z-m>36.1915</z-m>
    <pitch-deg> 0.00</pitch-deg>
    <heading-deg>0.0 </heading-deg>
  </offsets>
</model>

<model>
  <path>Models/Effects/pos_lamp_red_light_2st.xml</path>
  <offsets>
    <x-m>550.372</x-m>
    <y-m>216.846</y-m>
    <z-m>36.1915</z-m>
    <pitch-deg> 0.00</pitch-deg>
    <heading-deg>0.0 </heading-deg>
  </offsets>
</model>

<model>
  <path>Models/Effects/pos_lamp_red_light_2st.xml</path>
  <offsets>
    <x-m>560.457</x-m>
    <y-m>193.862</y-m>
    <z-m>36.1915</z-m>
    <pitch-deg> 0.00</pitch-deg>
    <heading-deg>0.0 </heading-deg>
  </offsets>
</model>

<model>
  <path>Models/Effects/pos_lamp_red_light_2st.xml</path>
  <offsets>
    <x-m>522.477</x-m>
    <y-m>204.589</y-m>
    <z-m>36.1915</z-m>
    <pitch-deg> 0.00</pitch-deg>
    <heading-deg>0.0 </heading-deg>
  </offsets>
</model>

<model>
  <path>Models/Effects/pos_lamp_red_light_2st.xml</path>
  <offsets>
    <x-m>207.768</x-m>
    <y-m>396.342</y-m>
    <z-m>48.0033</z-m>
    <pitch-deg> 0.00</pitch-deg>
    <heading-deg>0.0 </heading-deg>
  </offsets>
</model>

<model>
  <path>Models/Effects/pos_lamp_red_light_2st.xml</path>
  <offsets>
    <x-m>195.831</x-m>
    <y-m>351.513</y-m>
    <z-m>48.0033</z-m>
    <pitch-deg> 0.00</pitch-deg>
    <heading-deg>0.0 </heading-deg>
  </offsets>
</model>

<model>
  <path>Models/Effects/pos_lamp_red_light_2st.xml</path>
  <offsets>
    <x-m>198.887</x-m>
    <y-m>371.97</y-m>
    <z-m>48.0033</z-m>
    <pitch-deg> 0.00</pitch-deg>
    <heading-deg>0.0 </heading-deg>
  </offsets>
</model>

<model>
  <path>Models/Effects/pos_lamp_red_light_2st.xml</path>
  <offsets>
    <x-m>195.597</x-m>
    <y-m>379.301</y-m>
    <z-m>48.0033</z-m>
    <pitch-deg> 0.00</pitch-deg>
    <heading-deg>0.0 </heading-deg>
  </offsets>
</model>

<model>
  <path>Models/Effects/pos_lamp_red_light_2st.xml</path>
  <offsets>
    <x-m>851.79</x-m>
    <y-m>8011.53</y-m>
    <z-m>27.9619</z-m>
    <pitch-deg> 0.00</pitch-deg>
    <heading-deg>0.0 </heading-deg>
  </offsets>
</model>

<model>
  <path>Models/Effects/pos_lamp_red_light_2st.xml</path>
  <offsets>
    <x-m>875.35</x-m>
    <y-m>8002.03</y-m>
    <z-m>27.9619</z-m>
    <pitch-deg> 0.00</pitch-deg>
    <heading-deg>0.0 </heading-deg>
  </offsets>
</model>

<model>
  <path>Models/Effects/pos_lamp_red_light_2st.xml</path>
  <offsets>
    <x-m>880.175</x-m>
    <y-m>7984.93</y-m>
    <z-m>27.9619</z-m>
    <pitch-deg> 0.00</pitch-deg>
    <heading-deg>0.0 </heading-deg>
  </offsets>
</model>

<model>
  <path>Models/Effects/pos_lamp_red_light_2st.xml</path>
  <offsets>
    <x-m>896.991</x-m>
    <y-m>7973.99</y-m>
    <z-m>27.9619</z-m>
    <pitch-deg> 0.00</pitch-deg>
    <heading-deg>0.0 </heading-deg>
  </offsets>
</model>

<model>
  <path>Models/Effects/pos_lamp_red_light_2st.xml</path>
  <offsets>
    <x-m>260.798</x-m>
    <y-m>65.916</y-m>
    <z-m>39.4063</z-m>
    <pitch-deg> 0.00</pitch-deg>
    <heading-deg>0.0 </heading-deg>
  </offsets>
</model>

<model>
  <path>Models/Effects/pos_lamp_red_light_2st.xml</path>
  <offsets>
    <x-m>237.548</x-m>
    <y-m>75.1372</y-m>
    <z-m>39.4063</z-m>
    <pitch-deg> 0.00</pitch-deg>
    <heading-deg>0.0 </heading-deg>
  </offsets>
</model>

<model>
  <path>Models/Effects/pos_lamp_red_light_2st.xml</path>
  <offsets>
    <x-m>239.406</x-m>
    <y-m>87.018</y-m>
    <z-m>39.4063</z-m>
    <pitch-deg> 0.00</pitch-deg>
    <heading-deg>0.0 </heading-deg>
  </offsets>
</model>

<model>
  <path>Models/Effects/pos_lamp_red_light_2st.xml</path>
  <offsets>
    <x-m>217.103</x-m>
    <y-m>98.6275</y-m>
    <z-m>39.4063</z-m>
    <pitch-deg> 0.00</pitch-deg>
    <heading-deg>0.0 </heading-deg>
  </offsets>
</model>

<model>
  <path>Models/Effects/pos_lamp_red_light_2st.xml</path>
  <offsets>
    <x-m>187.869</x-m>
    <y-m>37.278</y-m>
    <z-m>37.1181</z-m>
    <pitch-deg> 0.00</pitch-deg>
    <heading-deg>0.0 </heading-deg>
  </offsets>
</model>

<model>
  <path>Models/Effects/pos_lamp_red_light_2st.xml</path>
  <offsets>
    <x-m>162.603</x-m>
    <y-m>51.8283</y-m>
    <z-m>37.1181</z-m>
    <pitch-deg> 0.00</pitch-deg>
    <heading-deg>0.0 </heading-deg>
  </offsets>
</model>

<model>
  <path>Models/Effects/pos_lamp_red_light_2st.xml</path>
  <offsets>
    <x-m>164.848</x-m>
    <y-m>62.9402</y-m>
    <z-m>37.1181</z-m>
    <pitch-deg> 0.00</pitch-deg>
    <heading-deg>0.0 </heading-deg>
  </offsets>
</model>

<model>
  <path>Models/Effects/pos_lamp_red_light_2st.xml</path>
  <offsets>
    <x-m>144.727</x-m>
    <y-m>68.804</y-m>
    <z-m>37.1181</z-m>
    <pitch-deg> 0.00</pitch-deg>
    <heading-deg>0.0 </heading-deg>
  </offsets>
</model>

<model>
  <path>Models/Effects/pos_lamp_red_light_2st.xml</path>
  <offsets>
    <x-m>184.403</x-m>
    <y-m>45.2393</y-m>
    <z-m>37.3472</z-m>
    <pitch-deg> 0.00</pitch-deg>
    <heading-deg>0.0 </heading-deg>
  </offsets>
</model>

<model>
  <path>Models/Effects/pos_lamp_red_light_2st.xml</path>
  <offsets>
    <x-m>195.068</x-m>
    <y-m>89.7443</y-m>
    <z-m>37.3472</z-m>
    <pitch-deg> 0.00</pitch-deg>
    <heading-deg>0.0 </heading-deg>
  </offsets>
</model>

<model>
  <path>Models/Effects/pos_lamp_red_light_2st.xml</path>
  <offsets>
    <x-m>191.214</x-m>
    <y-m>74.0605</y-m>
    <z-m>37.3472</z-m>
    <pitch-deg> 0.00</pitch-deg>
    <heading-deg>0.0 </heading-deg>
  </offsets>
</model>

<model>
  <path>Models/Effects/pos_lamp_red_light_2st.xml</path>
  <offsets>
    <x-m>195.789</x-m>
    <y-m>65.3029</y-m>
    <z-m>37.3472</z-m>
    <pitch-deg> 0.00</pitch-deg>
    <heading-deg>0.0 </heading-deg>
  </offsets>
</model>

<model>
  <path>Models/Effects/pos_lamp_red_light_2st.xml</path>
  <offsets>
    <x-m>851.79</x-m>
    <y-m>8011.53</y-m>
    <z-m>28.5929</z-m>
    <pitch-deg> 0.00</pitch-deg>
    <heading-deg>0.0 </heading-deg>
  </offsets>
</model>

<model>
  <path>Models/Effects/pos_lamp_red_light_2st.xml</path>
  <offsets>
    <x-m>848.635</x-m>
    <y-m>7972.53</y-m>
    <z-m>28.5929</z-m>
    <pitch-deg> 0.00</pitch-deg>
    <heading-deg>0.0 </heading-deg>
  </offsets>
</model>

<model>
  <path>Models/Effects/pos_lamp_red_light_2st.xml</path>
  <offsets>
    <x-m>851.579</x-m>
    <y-m>7980.73</y-m>
    <z-m>28.5929</z-m>
    <pitch-deg> 0.00</pitch-deg>
    <heading-deg>0.0 </heading-deg>
  </offsets>
</model>

<model>
  <path>Models/Effects/pos_lamp_red_light_2st.xml</path>
  <offsets>
    <x-m>841.275</x-m>
    <y-m>7989.06</y-m>
    <z-m>28.5929</z-m>
    <pitch-deg> 0.00</pitch-deg>
    <heading-deg>0.0 </heading-deg>
  </offsets>
</model>

<model>
  <path>Models/Effects/pos_lamp_red_light_2st.xml</path>
  <offsets>
    <x-m>561.836</x-m>
    <y-m>144.962</y-m>
    <z-m>34.0086</z-m>
    <pitch-deg> 0.00</pitch-deg>
    <heading-deg>0.0 </heading-deg>
  </offsets>
</model>

<model>
  <path>Models/Effects/pos_lamp_red_light_2st.xml</path>
  <offsets>
    <x-m>590.915</x-m>
    <y-m>123.422</y-m>
    <z-m>34.0086</z-m>
    <pitch-deg> 0.00</pitch-deg>
    <heading-deg>0.0 </heading-deg>
  </offsets>
</model>

<model>
  <path>Models/Effects/pos_lamp_red_light_2st.xml</path>
  <offsets>
    <x-m>572.371</x-m>
    <y-m>120.796</y-m>
    <z-m>34.0086</z-m>
    <pitch-deg> 0.00</pitch-deg>
    <heading-deg>0.0 </heading-deg>
  </offsets>
</model>

<model>
  <path>Models/Effects/pos_lamp_red_light_2st.xml</path>
  <offsets>
    <x-m>604.568</x-m>
    <y-m>118.613</y-m>
    <z-m>34.0086</z-m>
    <pitch-deg> 0.00</pitch-deg>
    <heading-deg>0.0 </heading-deg>
  </offsets>
</model>

<model>
  <path>Models/Effects/pos_lamp_red_light_2st.xml</path>
  <offsets>
    <x-m>60.2608</x-m>
    <y-m>342.83</y-m>
    <z-m>58.5765</z-m>
    <pitch-deg> 0.00</pitch-deg>
    <heading-deg>0.0 </heading-deg>
  </offsets>
</model>

<model>
  <path>Models/Effects/pos_lamp_red_light_2st.xml</path>
  <offsets>
    <x-m>75.1449</x-m>
    <y-m>343.336</y-m>
    <z-m>58.5765</z-m>
    <pitch-deg> 0.00</pitch-deg>
    <heading-deg>0.0 </heading-deg>
  </offsets>
</model>

<model>
  <path>Models/Effects/pos_lamp_red_light_2st.xml</path>
  <offsets>
    <x-m>83.3704</x-m>
    <y-m>336.172</y-m>
    <z-m>58.5765</z-m>
    <pitch-deg> 0.00</pitch-deg>
    <heading-deg>0.0 </heading-deg>
  </offsets>
</model>

<model>
  <path>Models/Effects/pos_lamp_red_light_2st.xml</path>
  <offsets>
    <x-m>81.6765</x-m>
    <y-m>361.867</y-m>
    <z-m>58.5765</z-m>
    <pitch-deg> 0.00</pitch-deg>
    <heading-deg>0.0 </heading-deg>
  </offsets>
</model>

<model>
  <path>Models/Effects/pos_lamp_red_light_2st.xml</path>
  <offsets>
    <x-m>131.218</x-m>
    <y-m>370.859</y-m>
    <z-m>62.8379</z-m>
    <pitch-deg> 0.00</pitch-deg>
    <heading-deg>0.0 </heading-deg>
  </offsets>
</model>

<model>
  <path>Models/Effects/pos_lamp_red_light_2st.xml</path>
  <offsets>
    <x-m>119.547</x-m>
    <y-m>323.39</y-m>
    <z-m>62.8379</z-m>
    <pitch-deg> 0.00</pitch-deg>
    <heading-deg>0.0 </heading-deg>
  </offsets>
</model>

<model>
  <path>Models/Effects/pos_lamp_red_light_2st.xml</path>
  <offsets>
    <x-m>122.107</x-m>
    <y-m>348.017</y-m>
    <z-m>62.8379</z-m>
    <pitch-deg> 0.00</pitch-deg>
    <heading-deg>0.0 </heading-deg>
  </offsets>
</model>

<model>
  <path>Models/Effects/pos_lamp_red_light_2st.xml</path>
  <offsets>
    <x-m>118.231</x-m>
    <y-m>357.201</y-m>
    <z-m>62.8379</z-m>
    <pitch-deg> 0.00</pitch-deg>
    <heading-deg>0.0 </heading-deg>
  </offsets>
</model>

<model>
  <path>Models/Effects/pos_lamp_red_light_2st.xml</path>
  <offsets>
    <x-m>131.218</x-m>
    <y-m>370.859</y-m>
    <z-m>50.5529</z-m>
    <pitch-deg> 0.00</pitch-deg>
    <heading-deg>0.0 </heading-deg>
  </offsets>
</model>

<model>
  <path>Models/Effects/pos_lamp_red_light_2st.xml</path>
  <offsets>
    <x-m>147.034</x-m>
    <y-m>368.414</y-m>
    <z-m>50.5529</z-m>
    <pitch-deg> 0.00</pitch-deg>
    <heading-deg>0.0 </heading-deg>
  </offsets>
</model>

<model>
  <path>Models/Effects/pos_lamp_red_light_2st.xml</path>
  <offsets>
    <x-m>155.735</x-m>
    <y-m>361.79</y-m>
    <z-m>50.5529</z-m>
    <pitch-deg> 0.00</pitch-deg>
    <heading-deg>0.0 </heading-deg>
  </offsets>
</model>

<model>
  <path>Models/Effects/pos_lamp_red_light_2st.xml</path>
  <offsets>
    <x-m>154.384</x-m>
    <y-m>389.731</y-m>
    <z-m>50.5529</z-m>
    <pitch-deg> 0.00</pitch-deg>
    <heading-deg>0.0 </heading-deg>
  </offsets>
</model>

<model>
  <path>Models/Effects/pos_lamp_red_light_2st.xml</path>
  <offsets>
    <x-m>499.006</x-m>
    <y-m>8255.35</y-m>
    <z-m>58.9895</z-m>
    <pitch-deg> 0.00</pitch-deg>
    <heading-deg>0.0 </heading-deg>
  </offsets>
</model>

<model>
  <path>Models/Effects/pos_lamp_red_light_2st.xml</path>
  <offsets>
    <x-m>489.993</x-m>
    <y-m>8210.11</y-m>
    <z-m>58.9895</z-m>
    <pitch-deg> 0.00</pitch-deg>
    <heading-deg>0.0 </heading-deg>
  </offsets>
</model>

<model>
  <path>Models/Effects/pos_lamp_red_light_2st.xml</path>
  <offsets>
    <x-m>489.044</x-m>
    <y-m>8234.66</y-m>
    <z-m>58.9895</z-m>
    <pitch-deg> 0.00</pitch-deg>
    <heading-deg>0.0 </heading-deg>
  </offsets>
</model>

<model>
  <path>Models/Effects/pos_lamp_red_light_2st.xml</path>
  <offsets>
    <x-m>484.923</x-m>
    <y-m>8243.4</y-m>
    <z-m>58.9895</z-m>
    <pitch-deg> 0.00</pitch-deg>
    <heading-deg>0.0 </heading-deg>
  </offsets>
</model>

<model>
  <path>Models/Effects/pos_lamp_red_light_2st.xml</path>
  <offsets>
    <x-m>329.33</x-m>
    <y-m>105.877</y-m>
    <z-m>55.3046</z-m>
    <pitch-deg> 0.00</pitch-deg>
    <heading-deg>0.0 </heading-deg>
  </offsets>
</model>

<model>
  <path>Models/Effects/pos_lamp_red_light_2st.xml</path>
  <offsets>
    <x-m>340.016</x-m>
    <y-m>152.191</y-m>
    <z-m>55.3046</z-m>
    <pitch-deg> 0.00</pitch-deg>
    <heading-deg>0.0 </heading-deg>
  </offsets>
</model>

<model>
  <path>Models/Effects/pos_lamp_red_light_2st.xml</path>
  <offsets>
    <x-m>339.066</x-m>
    <y-m>129.547</y-m>
    <z-m>55.3046</z-m>
    <pitch-deg> 0.00</pitch-deg>
    <heading-deg>0.0 </heading-deg>
  </offsets>
</model>

<model>
  <path>Models/Effects/pos_lamp_red_light_2st.xml</path>
  <offsets>
    <x-m>342.968</x-m>
    <y-m>120.162</y-m>
    <z-m>55.3046</z-m>
    <pitch-deg> 0.00</pitch-deg>
    <heading-deg>0.0 </heading-deg>
  </offsets>
</model>

<model>
  <path>Models/Effects/pos_lamp_red_light_2st.xml</path>
  <offsets>
    <x-m>771.664</x-m>
    <y-m>8009.9</y-m>
    <z-m>47.0676</z-m>
    <pitch-deg> 0.00</pitch-deg>
    <heading-deg>0.0 </heading-deg>
  </offsets>
</model>

<model>
  <path>Models/Effects/pos_lamp_red_light_2st.xml</path>
  <offsets>
    <x-m>748.233</x-m>
    <y-m>8018.74</y-m>
    <z-m>47.0676</z-m>
    <pitch-deg> 0.00</pitch-deg>
    <heading-deg>0.0 </heading-deg>
  </offsets>
</model>

<model>
  <path>Models/Effects/pos_lamp_red_light_2st.xml</path>
  <offsets>
    <x-m>749.775</x-m>
    <y-m>8031.06</y-m>
    <z-m>47.0676</z-m>
    <pitch-deg> 0.00</pitch-deg>
    <heading-deg>0.0 </heading-deg>
  </offsets>
</model>

<model>
  <path>Models/Effects/pos_lamp_red_light_2st.xml</path>
  <offsets>
    <x-m>725.92</x-m>
    <y-m>8040.68</y-m>
    <z-m>47.0676</z-m>
    <pitch-deg> 0.00</pitch-deg>
    <heading-deg>0.0 </heading-deg>
  </offsets>
</model>

<model>
  <path>Models/Effects/pos_lamp_red_light_2st.xml</path>
  <offsets>
    <x-m>338.123</x-m>
    <y-m>8258.23</y-m>
    <z-m>68.6218</z-m>
    <pitch-deg> 0.00</pitch-deg>
    <heading-deg>0.0 </heading-deg>
  </offsets>
</model>

<model>
  <path>Models/Effects/pos_lamp_red_light_2st.xml</path>
  <offsets>
    <x-m>357.853</x-m>
    <y-m>8251.05</y-m>
    <z-m>68.6218</z-m>
    <pitch-deg> 0.00</pitch-deg>
    <heading-deg>0.0 </heading-deg>
  </offsets>
</model>

<model>
  <path>Models/Effects/pos_lamp_red_light_2st.xml</path>
  <offsets>
    <x-m>358.749</x-m>
    <y-m>8276.46</y-m>
    <z-m>68.6218</z-m>
    <pitch-deg> 0.00</pitch-deg>
    <heading-deg>0.0 </heading-deg>
  </offsets>
</model>

<model>
  <path>Models/Effects/pos_lamp_red_light_2st.xml</path>
  <offsets>
    <x-m>351.131</x-m>
    <y-m>8270.33</y-m>
    <z-m>68.6218</z-m>
    <pitch-deg> 0.00</pitch-deg>
    <heading-deg>0.0 </heading-deg>
  </offsets>
</model>

<model>
  <path>Models/Effects/pos_lamp_red_light_2st.xml</path>
  <offsets>
    <x-m>-126.014</x-m>
    <y-m>383.678</y-m>
    <z-m>68.0322</z-m>
    <pitch-deg> 0.00</pitch-deg>
    <heading-deg>0.0 </heading-deg>
  </offsets>
</model>

<model>
  <path>Models/Effects/pos_lamp_red_light_2st.xml</path>
  <offsets>
    <x-m>-134.684</x-m>
    <y-m>352.271</y-m>
    <z-m>68.0322</z-m>
    <pitch-deg> 0.00</pitch-deg>
    <heading-deg>0.0 </heading-deg>
  </offsets>
</model>

<model>
  <path>Models/Effects/pos_lamp_red_light_2st.xml</path>
  <offsets>
    <x-m>-108.626</x-m>
    <y-m>352.76</y-m>
    <z-m>68.0322</z-m>
    <pitch-deg> 0.00</pitch-deg>
    <heading-deg>0.0 </heading-deg>
  </offsets>
</model>

<model>
  <path>Models/Effects/pos_lamp_red_light_2st.xml</path>
  <offsets>
    <x-m>-114.941</x-m>
    <y-m>363.891</y-m>
    <z-m>68.0322</z-m>
    <pitch-deg> 0.00</pitch-deg>
    <heading-deg>0.0 </heading-deg>
  </offsets>
</model>

<model>
  <path>Models/Effects/pos_lamp_red_light_2st.xml</path>
  <offsets>
    <x-m>-144.108</x-m>
    <y-m>376.583</y-m>
    <z-m>63.7503</z-m>
    <pitch-deg> 0.00</pitch-deg>
    <heading-deg>0.0 </heading-deg>
  </offsets>
</model>

<model>
  <path>Models/Effects/pos_lamp_red_light_2st.xml</path>
  <offsets>
    <x-m>-134.035</x-m>
    <y-m>410.949</y-m>
    <z-m>63.7503</z-m>
    <pitch-deg> 0.00</pitch-deg>
    <heading-deg>0.0 </heading-deg>
  </offsets>
</model>

<model>
  <path>Models/Effects/pos_lamp_red_light_2st.xml</path>
  <offsets>
    <x-m>-150.862</x-m>
    <y-m>404.357</y-m>
    <z-m>63.7503</z-m>
    <pitch-deg> 0.00</pitch-deg>
    <heading-deg>0.0 </heading-deg>
  </offsets>
</model>

<model>
  <path>Models/Effects/pos_lamp_red_light_2st.xml</path>
  <offsets>
    <x-m>-148.539</x-m>
    <y-m>388.022</y-m>
    <z-m>63.7503</z-m>
    <pitch-deg> 0.00</pitch-deg>
    <heading-deg>0.0 </heading-deg>
  </offsets>
</model>

<model>
  <path>Models/Effects/pos_lamp_red_light_2st.xml</path>
  <offsets>
    <x-m>471.046</x-m>
    <y-m>103.031</y-m>
    <z-m>81.6658</z-m>
    <pitch-deg> 0.00</pitch-deg>
    <heading-deg>0.0 </heading-deg>
  </offsets>
</model>

<model>
  <path>Models/Effects/pos_lamp_red_light_2st.xml</path>
  <offsets>
    <x-m>525.934</x-m>
    <y-m>84.7663</y-m>
    <z-m>81.6658</z-m>
    <pitch-deg> 0.00</pitch-deg>
    <heading-deg>0.0 </heading-deg>
  </offsets>
</model>

<model>
  <path>Models/Effects/pos_lamp_red_light_2st.xml</path>
  <offsets>
    <x-m>517.366</x-m>
    <y-m>102.959</y-m>
    <z-m>81.6658</z-m>
    <pitch-deg> 0.00</pitch-deg>
    <heading-deg>0.0 </heading-deg>
  </offsets>
</model>

<model>
  <path>Models/Effects/pos_lamp_red_light_2st.xml</path>
  <offsets>
    <x-m>490.172</x-m>
    <y-m>127.03</y-m>
    <z-m>81.6658</z-m>
    <pitch-deg> 0.00</pitch-deg>
    <heading-deg>0.0 </heading-deg>
  </offsets>
</model>

<model>
  <path>Models/Effects/pos_lamp_red_light_2st.xml</path>
  <offsets>
    <x-m>-213.072</x-m>
    <y-m>175.632</y-m>
    <z-m>83.754</z-m>
    <pitch-deg> 0.00</pitch-deg>
    <heading-deg>0.0 </heading-deg>
  </offsets>
</model>

<model>
  <path>Models/Effects/pos_lamp_red_light_2st.xml</path>
  <offsets>
    <x-m>-238.618</x-m>
    <y-m>132.834</y-m>
    <z-m>83.754</z-m>
    <pitch-deg> 0.00</pitch-deg>
    <heading-deg>0.0 </heading-deg>
  </offsets>
</model>

<model>
  <path>Models/Effects/pos_lamp_red_light_2st.xml</path>
  <offsets>
    <x-m>-200.947</x-m>
    <y-m>148.437</y-m>
    <z-m>83.754</z-m>
    <pitch-deg> 0.00</pitch-deg>
    <heading-deg>0.0 </heading-deg>
  </offsets>
</model>

<model>
  <path>Models/Effects/pos_lamp_red_light_2st.xml</path>
  <offsets>
    <x-m>-204.535</x-m>
    <y-m>156.471</y-m>
    <z-m>83.754</z-m>
    <pitch-deg> 0.00</pitch-deg>
    <heading-deg>0.0 </heading-deg>
  </offsets>
</model>

<model>
  <path>Models/Effects/pos_lamp_red_light_2st.xml</path>
  <offsets>
    <x-m>237.024</x-m>
    <y-m>-34.9308</y-m>
    <z-m>103.941</z-m>
    <pitch-deg> 0.00</pitch-deg>
    <heading-deg>0.0 </heading-deg>
  </offsets>
</model>

<model>
  <path>Models/Effects/pos_lamp_red_light_2st.xml</path>
  <offsets>
    <x-m>165.276</x-m>
    <y-m>-12.135</y-m>
    <z-m>103.941</z-m>
    <pitch-deg> 0.00</pitch-deg>
    <heading-deg>0.0 </heading-deg>
  </offsets>
</model>

<model>
  <path>Models/Effects/pos_lamp_red_light_2st.xml</path>
  <offsets>
    <x-m>208.333</x-m>
    <y-m>-33.2189</y-m>
    <z-m>103.941</z-m>
    <pitch-deg> 0.00</pitch-deg>
    <heading-deg>0.0 </heading-deg>
  </offsets>
</model>

<model>
  <path>Models/Effects/pos_lamp_red_light_2st.xml</path>
  <offsets>
    <x-m>182.785</x-m>
    <y-m>-45.4092</y-m>
    <z-m>103.941</z-m>
    <pitch-deg> 0.00</pitch-deg>
    <heading-deg>0.0 </heading-deg>
  </offsets>
</model>

<model>
  <path>Models/Effects/pos_lamp_red_light_2st.xml</path>
  <offsets>
    <x-m>-566.407</x-m>
    <y-m>1.26644</y-m>
    <z-m>74.1549</z-m>
    <pitch-deg> 0.00</pitch-deg>
    <heading-deg>0.0 </heading-deg>
  </offsets>
</model>

<model>
  <path>Models/Effects/pos_lamp_red_light_2st.xml</path>
  <offsets>
    <x-m>-553.732</x-m>
    <y-m>-22.6107</y-m>
    <z-m>74.1549</z-m>
    <pitch-deg> 0.00</pitch-deg>
    <heading-deg>0.0 </heading-deg>
  </offsets>
</model>

<model>
  <path>Models/Effects/pos_lamp_red_light_2st.xml</path>
  <offsets>
    <x-m>-526.336</x-m>
    <y-m>-15.9734</y-m>
    <z-m>74.1549</z-m>
    <pitch-deg> 0.00</pitch-deg>
    <heading-deg>0.0 </heading-deg>
  </offsets>
</model>

<model>
  <path>Models/Effects/pos_lamp_red_light_2st.xml</path>
  <offsets>
    <x-m>-542.494</x-m>
    <y-m>8.42008</y-m>
    <z-m>74.1549</z-m>
    <pitch-deg> 0.00</pitch-deg>
    <heading-deg>0.0 </heading-deg>
  </offsets>
</model>

<model>
  <path>Models/Effects/pos_lamp_red_light_2st.xml</path>
  <offsets>
    <x-m>668.494</x-m>
    <y-m>-55.7828</y-m>
    <z-m>116.256</z-m>
    <pitch-deg> 0.00</pitch-deg>
    <heading-deg>0.0 </heading-deg>
  </offsets>
</model>

<model>
  <path>Models/Effects/pos_lamp_red_light_2st.xml</path>
  <offsets>
    <x-m>660.233</x-m>
    <y-m>6.68053</y-m>
    <z-m>116.256</z-m>
    <pitch-deg> 0.00</pitch-deg>
    <heading-deg>0.0 </heading-deg>
  </offsets>
</model>

<model>
  <path>Models/Effects/pos_lamp_red_light_2st.xml</path>
  <offsets>
    <x-m>643.037</x-m>
    <y-m>42.4652</y-m>
    <z-m>116.256</z-m>
    <pitch-deg> 0.00</pitch-deg>
    <heading-deg>0.0 </heading-deg>
  </offsets>
</model>

<model>
  <path>Models/Effects/pos_lamp_red_light_2st.xml</path>
  <offsets>
    <x-m>626.117</x-m>
    <y-m>42.4136</y-m>
    <z-m>116.256</z-m>
    <pitch-deg> 0.00</pitch-deg>
    <heading-deg>0.0 </heading-deg>
  </offsets>
</model>

<model>
  <path>Models/Effects/pos_lamp_red_light_2st.xml</path>
  <offsets>
    <x-m>25.1917</x-m>
    <y-m>682.237</y-m>
    <z-m>79.9015</z-m>
    <pitch-deg> 0.00</pitch-deg>
    <heading-deg>0.0 </heading-deg>
  </offsets>
</model>

<model>
  <path>Models/Effects/pos_lamp_red_light_2st.xml</path>
  <offsets>
    <x-m>87.645</x-m>
    <y-m>712.453</y-m>
    <z-m>79.9015</z-m>
    <pitch-deg> 0.00</pitch-deg>
    <heading-deg>0.0 </heading-deg>
  </offsets>
</model>

<model>
  <path>Models/Effects/pos_lamp_red_light_2st.xml</path>
  <offsets>
    <x-m>135.459</x-m>
    <y-m>733.945</y-m>
    <z-m>79.9015</z-m>
    <pitch-deg> 0.00</pitch-deg>
    <heading-deg>0.0 </heading-deg>
  </offsets>
</model>

<model>
  <path>Models/Effects/pos_lamp_red_light_2st.xml</path>
  <offsets>
    <x-m>118.96</x-m>
    <y-m>751.373</y-m>
    <z-m>79.9015</z-m>
    <pitch-deg> 0.00</pitch-deg>
    <heading-deg>0.0 </heading-deg>
  </offsets>
</model>
</PropertyList>
